mspass_launcher/__init__.py
mspass_launcher/desktop.py
mspass_launcher/hpc.py
mspass_launcher/util.py
mspass_launcher/data/yaml/DesktopCluster.yaml
mspass_launcher/data/yaml/HPCClusterLauncher.yaml
mspass_launcher/data/yaml/MsPASSDesktopGUI.yaml
mspass_launcher/scripts/__init__.py
mspass_launcher/scripts/mspass_desktop.py
mspass_launcher-0.1.1.dist-info/licenses/LICENSE
mspass_launcher-0.1.1.dist-info/METADATA
mspass_launcher-0.1.1.dist-info/WHEEL
mspass_launcher-0.1.1.dist-info/entry_points.txt
mspass_launcher-0.1.1.dist-info/top_level.txt
mspass_launcher-0.1.1.dist-info/RECORD
