Metadata-Version: 2.4
Name: mspass-launcher
Version: 0.1.1
Summary: A launcher for MsPASS on desktop and HPC clusters.
Author-email: "Gary L. Pavlis" <help@mspass.org>
License: BSD 3-Clause License
Project-URL: Homepage, https://github.com/mspass-team/mspass_launcher
Project-URL: Repository, https://github.com/mspass-team/mspass_launcher
Classifier: Development Status :: 3 - Alpha
Classifier: Intended Audience :: Science/Research
Classifier: Programming Language :: Python :: 3
Classifier: Programming Language :: Python :: 3.7
Classifier: Programming Language :: Python :: 3.8
Classifier: Programming Language :: Python :: 3.9
Classifier: Programming Language :: Python :: 3.10
Classifier: Programming Language :: Python :: 3.11
Classifier: Programming Language :: Python :: 3.12
Classifier: Operating System :: OS Independent
Classifier: Topic :: Scientific/Engineering
Requires-Python: >=3.7
License-File: LICENSE
Requires-Dist: pyyaml>=5.1
Dynamic: license-file
